fastre-0.2.9.dist-info/METADATA
fastre-0.2.9.dist-info/WHEEL
fastre-0.2.9.dist-info/licenses/LICENSE
fastre/__init__.py
fastre/__init__.pyi
fastre/fastre.cpython-310-powerpc64le-linux-gnu.so
fastre/py.typed
fastre-0.2.9.dist-info/RECORD
