Metadata-Version: 2.4
Name: fastre
Version: 0.2.9
Classifier: Programming Language :: Rust
Classifier: Programming Language :: Python :: Implementation :: CPython
Classifier: Programming Language :: Python :: Implementation :: PyPy
License-File: LICENSE
Summary: A Lightning Fast ⚡ Rust-based regex crate wrapper for Python3 to get faster performance. 👾
Maintainer-email: Hugo Pendlebury <hugo.pendlebury@gmail.com>
License: MIT
Requires-Python: >=3.8
Project-URL: Homepage, https://github.com/hugopendlebury/fastre
Project-URL: Repository, https://github.com/hugopendlebury/fastre.git
Project-URL: Bug Tracker, https://github.com/fastre/fastre/issues
